splitpea/__init__.py
splitpea/core.py
splitpea/exons.py
splitpea/get_background_ppi.py
splitpea/get_consensus_network.py
splitpea/grab_stats.py
splitpea/main.py
splitpea/parser.py
splitpea/plot_network.py
splitpea/preprocess_pooled.py
splitpea/src/mouse_ref/ddi_0.5.dat
splitpea/src/mouse_ref/human_ppi_0.5.dat
splitpea/src/mouse_ref/mmu_mapping_all.txt
splitpea/src/mouse_ref/mouse_entrez_pfam.txt
splitpea/src/mouse_ref/mouse_ortholog_ppi.dat
splitpea/src/mouse_ref/mouse_ortholog_ppi_map.txt
splitpea/src/mouse_ref/mouse_pfam_genome_coords_sorted.txt.gz
splitpea/src/mouse_ref/mouse_pfam_genome_coords_sorted.txt.gz.tbi
splitpea/src/mouse_ref/mouse_ppi.dat
splitpea/src/mouse_ref/mouse_ppi_map.txt
splitpea/src/reference/ddi_0.5.dat
splitpea/src/reference/hsa_mapping_all.txt
splitpea/src/reference/human_entrez_pfam.txt
splitpea/src/reference/human_pfam_genome_coords_sorted.txt.gz
splitpea/src/reference/human_pfam_genome_coords_sorted.txt.gz.tbi
splitpea/src/reference/human_ppi_0.5.dat
splitpea/src/reference/human_ppi_ddi_bg.centralities.txt
splitpea/src/reference/human_ppi_ddi_bg.pickle
splitpea-0.1.1.dist-info/METADATA
splitpea-0.1.1.dist-info/WHEEL
splitpea-0.1.1.dist-info/entry_points.txt
splitpea-0.1.1.dist-info/top_level.txt
splitpea-0.1.1.dist-info/RECORD
