Metadata-Version: 2.4
Name: splitpea
Version: 0.1.1
Summary: Splitpea: method for calculating network rewiring changes due to splicing
Home-page: https://github.com/ylaboratory/splitpea_package
Author: Jeffrey Zhong, Alyssa Cantu, Ruth Dannenfelser, Vicky Yao
License: BSD-3-Clause
Classifier: Programming Language :: Python :: 3.8
Classifier: Operating System :: OS Independent
Requires-Python: >=3.8
Requires-Dist: numpy
Requires-Dist: networkx
Requires-Dist: intervaltree
Requires-Dist: ipykernel
Requires-Dist: matplotlib
Requires-Dist: plotnine
Requires-Dist: scikit-learn
Requires-Dist: adjustText
Requires-Dist: importlib_resources
Requires-Dist: requests
Dynamic: author
Dynamic: classifier
Dynamic: description
Dynamic: description-content-type
Dynamic: home-page
Dynamic: license
Dynamic: requires-dist
Dynamic: requires-python
Dynamic: summary
